{
  "date": "2019-12-12T23:00:00.000Z",
  "title": "Internationale Gesellschaft Orientalischer Christen e.V.",
  "slug": "internationale-gesellschaft-orientalischer-christen-ev",
  "description": "Die IGOC unterstützt mit ihren Projekten Menschen im Orient direkt vor Ort. Die moderne Webseite hilft dabei direkt über die Neuigkeiten vor Ort zu informieren.",
  "tags": [
    "Webflow",
    "CMS"
  ],
  "featured": false,
  "image": "/img/1500x.ig-oc.de.jpg",
  "shortImage": "/img/short.ig-oc.de.jpg"
}